Workbook

Sheet Leia-me
A1: QUADRO DE RISCOS – CENTRAL
A2: Transição governamental 2026 · Ofício SETRAM/GABSEC nº 838/2026 · Ofício nº 02/2026 da Equipe de Transição, item 7 (quadro de riscos)
A3: Prazo de retorno informado no ofício: 28/10/2026
A5: STATUS: RASCUNHO PARA VALIDAÇÃO PELA ASSGER
A6: Os riscos, a probabilidade, o impacto, os responsáveis e as ações desta planilha são PROPOSTAS elaboradas a partir dos normativos da CENTRAL e dos ofícios da transição. Não houve entrevista com os gestores, que a Política de Gestão de Riscos (art. 23, I) prevê como forma de levantamento. Antes do envio, cada linha deve ser validada com a área responsável.
A8: Base normativa
A9: • Política de Gestão de Riscos, Conformidade e Controles Internos: categorias (art. 23, III), avaliação em baixo/médio/elevado/extremo (art. 20), tratamento evitar/mitigar/transferir/aceitar (arts. 21 e 26) e Matriz de Riscos (art. 25).
A10: • Regimento Interno da CENTRAL, art. 18: competências da ASSGER, incisos XXI, XXV e XXVI.
A11: • Lei nº 13.303/2016 e Decreto Estadual nº 46.188/2017.
A13: Como usar
A14: 1. Aba 'Critérios': escalas de probabilidade e impacto. Os limites dos níveis são sugestão, pois a política não fixa os valores numéricos. Ajuste se a ASSGER já tiver um padrão.
A15: 2. Aba 'Quadro de Riscos': preencha ou ajuste as colunas amarelas. Score e Nível são calculados automaticamente.
... A17: 4. Colunas 'A validar' marcam o que depende de confirmação da área responsável.

Sheet Quadro de Riscos
A1: QUADRO DE RISCOS DA CENTRAL – TRANSIÇÃO GOVERNAMENTAL 2026 (RASCUNHO PARA VALIDAÇÃO)
A2: Probabilidade, impacto, controles, responsáveis e prazos são propostas e devem ser validados com as áreas gestoras antes do envio.
A3: ID | B3: Categoria | C3: Processo / tema | D3: Evento de risco | E3: Causa / fonte | F3: Consequência / impacto | G3: Referência (origem da proposta) | H3: Controles existentes (A validar) | I3: Prob. (1-5) | J3: Impacto (1-5) | K3: Score | L3: Nível | M3: Tratamento | N3: Ação proposta (plano de ação) | O3: Responsável (A validar) | P3: Prazo (A validar) | Q3: Status
A4: R01 | B4: Estratégico | C4: Continuidade de programas e projetos | D4: Descontinuidade ou reprogramação de projetos e obras em curso na mudança de gestão | E4: Mudança de prioridades; falta de registro do estágio dos projetos; compromissos remanescentes não mapeados | F4: Atraso ou paralisação de projetos; perda de recursos já aplicados; desgaste institucional | G4: Ofício 02/2026 itens 2 e 3; Ofício 08/2026 itens 3 e 4; Estatuto, art. 3º | H4: A levantar com a área | I4: 3 | J4: 4 | K4: =I4*J4 | L4: =IF(K4>=17,"Extremo",IF(K4>=10,"Elevado",IF(K4>=5,"Médio","Baixo"))) | M4: Mitigar | N4: Consolidar relatório de projetos com estágio, medição, compromissos e licenciamento; indicar decisões irreversíveis antes de abr/2027 | O4: ASSPRIN / SUPLAN | P4: A definir | Q4: Proposta
A5: R02 | B5: Financeiro | C5: Execução orçamentária e financeira | D5: Contingenciamento de recursos pelo Estado para pagamento de pessoal, custeio ou capital | E5: Dependência de recursos do ente controlador; restrição fiscal | F5: Atraso em pagamentos a fornecedores e à folha; paralisação de contratos e obras | G5: Política de Gestão de Riscos, art. 23, III (Riscos Financeiros); Ofício 02/2026 item 8 | H5: A levantar com a área | I5: 4 | J5: 4 | K5: =I5*J5 | L5: =IF(K5>=17,"Extremo",IF(K5>=10,"Elevado",IF(K5>=5,"Médio","Baixo"))) | M5: Mitigar | N5: Priorizar despesas essenciais; dar visibilidade à programação por fonte e unidade orçamentária; plano de contingência financeira | O5: SUPFIC / GERORT | P5: A definir | Q5: Proposta
A6: R03 | B6: Financeiro | C6: Convênios e financiamentos | D6: Incerteza no recebimento de valores pactuados com órgãos de fomento, agentes financeiros ou convenentes | E6: Não cumprimento de condicionantes; atraso em prestação de contas; mudança de governo | F6: Perda de receita; devolução de recursos; interrupção de obras financiadas | G6: Política, art. 23, III; Ofício 08/2026 item 6 | H6: A levantar com a área | I6: 3 | J6: 4 | K6: =I6*J6 | L6: =IF(K6>=17,"Extremo",IF(K6>=10,"Elevado",IF(K6>=5,"Médio","Baixo"))) | M6: Mitigar | N6: Listar convênios e transferências com impacto recorrente; acompanhar prazos de prestação de contas e condicionantes | O6: SUPFIC / ASSPRIN | P6: A definir | Q6: Proposta
A7: R04 | B7: Financeiro | C7: Controles financeiros | D7: Controles ineficientes ou ausência de registro de movimentações financeiras | E7: Falhas de processo; segregação de funções insuficiente | F7: Erros contábeis; apontamentos de órgãos de controle; prejuízo | G7: Política, art. 23, III; Regimento, art. 18, XXIV | H7: A levantar com a área | I7: 2 | J7: 4 | K7: =I7*J7 | L7: =IF(K7>=17,"Extremo",IF(K7>=10,"Elevado",IF(K7>=5,"Médio","Baixo"))) | M7: Mitigar | N7: Revisar a segregação de funções e os registros das movimentações; testar os controles críticos | O7: SUPFIC / ASSGER | P7: A definir | Q7: Proposta
A8: R05 | B8: Operacional | C8: Contratos e licitações | D8: Vencimento de contratos entre out/2026 e abr/2027 sem prorrogação ou nova contratação a tempo | E8: Planejamento da contratação tardio; ciclo de licitação mais longo que o prazo de vigência | F8: Descontinuidade de serviços essenciais; contratações emergenciais ou irregulares | G8: Ofício 06/2026 itens 1 a 3 | H8: A levantar com a área | I8: 4 | J8: 4 | K8: =I8*J8 | L8: =IF(K8>=17,"Extremo",IF(K8>=10,"Elevado",IF(K8>=5,"Médio","Baixo"))) | M8: Mitigar | N8: Mapear contratos que vencem no período e definir providências de continuidade (prorrogação, nova licitação) com cronograma | O8: GERLIC / SUPADM | P8: A definir | Q8: Proposta
A9: R06 | B9: Operacional | C9: Gestão de pessoas | D9: Perda de conhecimento crítico e de pessoal-chave na transição | E9: Exoneração ou saída de dirigentes e ocupantes de cargos de confiança; falta de documentação dos processos | F9: Descontinuidade de rotinas; erros na tomada de decisão; atraso em entregas | G9: Ofício 02/2026 item 6 (recursos humanos); Regimento (SUPGEP) | H9: A levantar com a área | I9: 3 | J9: 3 | K9: =I9*J9 | L9: =IF(K9>=17,"Extremo",IF(K9>=10,"Elevado",IF(K9>=5,"Médio","Baixo"))) | M9: Mitigar | N9: Mapear posições críticas; documentar rotinas e passar o conhecimento antes da transição | O9: SUPGEP | P9: A definir | Q9: Proposta
A10: R07 | B10: Operacional | C10: Tecnologia da informação | D10: Falha, indisponibilidade ou acesso indevido a sistemas de informação, inclusive SEI-RJ e SIGA-RJ | E10: Mudança de perfis de acesso; backups e contingência insuficientes | F10: Perda de dados e de registros; paralisação de processos | G10: Ofício 02/2026 item 4 e item 6; Política, art. 23, III (Riscos Operacionais) | H10: A levantar com a área | I10: 2 | J10: 4 | K10: =I10*J10 | L10: =IF(K10>=17,"Extremo",IF(K10>=10,"Elevado",IF(K10>=5,"Médio","Baixo"))) | M10: Mitigar | N10: Inventariar sistemas e contratos associados; revisar perfis de acesso; testar backup e restauração | O10: GERTIN | P10: A definir | Q10: Proposta
A11: R08 | B11: Operacional | C11: Planos de contingência | D11: Ausência ou desatualização de planos de contingência dos principais processos de trabalho | E11: Processos ainda não mapeados ou revistos; falta de definição das condições mínimas de operação | F11: Resposta lenta a incidentes; interrupção de serviços essenciais | G11: Regimento, art. 18, XXI; Ofício 07/2026; Ofício 08/2026 itens 1 e 5 | H11: A levantar com a área | I11: 4 | J11: 3 | K11: =I11*J11 | L11: =IF(K11>=17,"Extremo",IF(K11>=10,"Elevado",IF(K11>=5,"Médio","Baixo"))) | M11: Mitigar | N11: Identificar os processos essenciais, definir condições mínimas de operação e responsáveis pelos planos de contingência | O11: ASSGER / áreas gestoras | P11: A definir | Q11: Proposta
A12: R09 | B12: Operacional | C12: Obras e manutenção | D12: Atraso, paralisação ou deficiência na manutenção e na conclusão de obras e intervenções | E12: Contratos vencendo; restrição financeira; pendências de licenciamento | F12: Prejuízo à operação do transporte sobre trilhos; custos de retomada | G12: Estatuto, art. 3º; Ofício 02/2026 item 3; Ofício 08/2026 item 3 | H12: A levantar com a área | I12: 3 | J12: 4 | K12: =I12*J12 | L12: =IF(K12>=17,"Extremo",IF(K12>=10,"Elevado",IF(K12>=5,"Médio","Baixo"))) | M12: Mitigar | N12: Consolidar estágio, medição e compromissos remanescentes; definir prioridades e riscos à continuidade | O12: SUPVIP / ASSPRIN | P12: A definir | Q12: Proposta
A13: R10 | B13: Operacional | C13: Patrimônio | D13: Inconsistência no inventário e na regularização de bens e imóveis | E13: Registros desatualizados; transferências a terceiros sem formalização | F13: Perda patrimonial; apontamentos de controle | G13: Regimento, art. 18, VIII; Ofício 02/2026 item 6 (patrimônio) | H13: A levantar com a área | I13: 3 | J13: 3 | K13: =I13*J13 | L13: =IF(K13>=17,"Extremo",IF(K13>=10,"Elevado",IF(K13>=5,"Médio","Baixo"))) | M13: Mitigar | N13: Conferir o inventário patrimonial e a documentação dos imóveis; tratar pendências de regularização | O13: SUPAT | P13: A definir | Q13: Proposta
A14: R11 | B14: Regulamentar | C14: Órgãos de controle | D14: Não atendimento de recomendações, determinações e prazos de órgãos de controle (TCE-RJ, TCU, CGE) | E14: Falta de controle central dos prazos; troca de responsáveis na transição | F14: Sanções; multas; responsabilização de dirigentes | G14: Ofício 07/2026; Regimento, art. 18, VII e XXII | H14: A levantar com a área | I14: 3 | J14: 4 | K14: =I14*J14 | L14: =IF(K14>=17,"Extremo",IF(K14>=10,"Elevado",IF(K14>=5,"Médio","Baixo"))) | M14: Mitigar | N14: Consolidar as pendências e os prazos num quadro único, com responsável por item (em conjunto com o item 7 do ofício) | O14: ASSGER / ASSJUR / AUD | P14: A definir | Q14: Proposta
A15: R12 | B15: Regulamentar | C15: Conformidade legal | D15: Não conformidade com a Lei nº 13.303/2016 e o Decreto nº 46.188/2017 (licitações, governança, divulgação, relatório anual) | E15: Normas internas desatualizadas; falta de verificação de aderência | F15: Sanções; nulidade de atos; perda de reputação | G15: Estatuto, art. 1º; Regimento, art. 18, III, VI, XVII e XVIII; Política, art. 23, III (Riscos Regulamentares) | H15: A levantar com a área | I15: 2 | J15: 4 | K15: =I15*J15 | L15: =IF(K15>=17,"Extremo",IF(K15>=10,"Elevado",IF(K15>=5,"Médio","Baixo"))) | M15: Mitigar | N15: Verificar a aderência das normas internas e dos processos; manter o Relatório Anual de Governança em dia | O15: ASSGER | P15: A definir | Q15: Proposta
... A18: R15 | B18: Estratégico | C18: Informação e transparência | D18: Fornecimento de informações inconsistentes, incompletas ou fora do prazo à Equipe de Transição | E18: Dados dispersos entre as áreas; prazo curto; ausência de data-base única | F18: Decisões equivocadas do novo governo; questionamento da gestão | G18: Ofício SETRAM/GABSEC nº 838/2026 (prazo 28/10/2026); Regimento, art. 18, I | H18: A levantar com a área | I18: 3 | J18: 3 | K18: =I18*J18 | L18: =IF(K18>=17,"Extremo",IF(K18>=10,"Elevado",IF(K18>=5,"Médio","Baixo"))) | M18: Mitigar | N18: Padronizar a data-base; validar os dados com as áreas antes do envio; manter registro das fontes | O18: ASSGER / PRESI | P18: A definir | Q18: Proposta

Sheet Critérios
A3: Escala de impacto
A4: Valor | B4: Classificação | C4: Descrição
A5: 1 | B5: Muito baixo | C5: Efeito desprezível, absorvido na rotina
A6: 2 | B6: Baixo | C6: Retrabalho ou atraso pontual, sem efeito na operação
A7: 3 | B7: Médio | C7: Atraso relevante de entregas ou exposição a questionamento de órgão de controle
A8: 4 | B8: Alto | C8: Interrupção parcial de atividade essencial, perda financeira relevante ou sanção
A9: 5 | B9: Muito alto | C9: Interrupção de atividade essencial, dano grave à imagem ou responsabilização de dirigentes
A12: Escala de probabilidade (detalhe)
A13: Valor | B13: Classificação | C13: Descrição
A14: 1 | B14: Muito baixa | C14: Ocorrência improvável; sem histórico
A15: 2 | B15: Baixa | C15: Pode ocorrer em circunstâncias excepcionais
A16: 3 | B16: Média | C16: Pode ocorrer; há histórico ou indício
A17: 4 | B17: Alta | C17: Provável de ocorrer no horizonte da transição (até abr/2027)
A18: 5 | B18: Muito alta | C18: Ocorrência esperada ou já em curso
A21: Nível de risco = Probabilidade × Impacto (art. 25, IV da Política)
A22: Nível | B22: Score | C22: Tratamento sugerido
A23: Baixo | B23: 1 a 4 | C23: Aceitar ou monitorar
A24: Médio | B24: 5 a 9 | C24: Mitigar com plano de ação da área gestora
A25: Elevado | B25: 10 a 16 | C25: Plano de ação prioritário
A26: Extremo | B26: 17 a 25 | C26: Plano de ação submetido à Diretoria Executiva (art. 27, III)
A28: Categorias (art. 23, III): Estratégico · Financeiro · Operacional · Regulamentar · Integridade
A29: Tratamento (arts. 21 e 26): Evitar · Mitigar · Transferir · Aceitar

Sheet Matriz de Riscos
A1: MATRIZ DE RISCOS (nº de riscos por célula e nível)
A2: Atualiza sozinha a partir da aba 'Quadro de Riscos'.
B4: IMPACTO | C4: IMPACTO → | I4: Resumo por nível
A5: PROBABILIDADE ↓ | C5: 1 | D5: 2 | E5: 3 | F5: 4 | G5: 5 | I5: Baixo | J5: =COUNTIF('Quadro de Riscos'!$L$4:$L$48,"Baixo")
B6: 5 | C6: =COUNTIFS('Quadro de Riscos'!$I$4:$I$48,5,'Quadro de Riscos'!$J$4:$J$48,1) | D6: =COUNTIFS('Quadro de Riscos'!$I$4:$I$48,5,'Quadro de Riscos'!$J$4:$J$48,2) | E6: =COUNTIFS('Quadro de Riscos'!$I$4:$I$48,5,'Quadro de Riscos'!$J$4:$J$48,3) | F6: =COUNTIFS('Quadro de Riscos'!$I$4:$I$48,5,'Quadro de Riscos'!$J$4:$J$48,4) | G6: =COUNTIFS('Quadro de Riscos'!$I$4:$I$48,5,'Quadro de Riscos'!$J$4:$J$48,5) | I6: Médio | J6: =COUNTIF('Quadro de Riscos'!$L$4:$L$48,"Médio")
B7: 4 | C7: =COUNTIFS('Quadro de Riscos'!$I$4:$I$48,4,'Quadro de Riscos'!$J$4:$J$48,1) | D7: =COUNTIFS('Quadro de Riscos'!$I$4:$I$48,4,'Quadro de Riscos'!$J$4:$J$48,2) | E7: =COUNTIFS('Quadro de Riscos'!$I$4:$I$48,4,'Quadro de Riscos'!$J$4:$J$48,3) | F7: =COUNTIFS('Quadro de Riscos'!$I$4:$I$48,4,'Quadro de Riscos'!$J$4:$J$48,4) | G7: =COUNTIFS('Quadro de Riscos'!$I$4:$I$48,4,'Quadro de Riscos'!$J$4:$J$48,5) | I7: Elevado | J7: =COUNTIF('Quadro de Riscos'!$L$4:$L$48,"Elevado")
B8: 3 | C8: =COUNTIFS('Quadro de Riscos'!$I$4:$I$48,3,'Quadro de Riscos'!$J$4:$J$48,1) | D8: =COUNTIFS('Quadro de Riscos'!$I$4:$I$48,3,'Quadro de Riscos'!$J$4:$J$48,2) | E8: =COUNTIFS('Quadro de Riscos'!$I$4:$I$48,3,'Quadro de Riscos'!$J$4:$J$48,3) | F8: =COUNTIFS('Quadro de Riscos'!$I$4:$I$48,3,'Quadro de Riscos'!$J$4:$J$48,4) | G8: =COUNTIFS('Quadro de Riscos'!$I$4:$I$48,3,'Quadro de Riscos'!$J$4:$J$48,5) | I8: Extremo | J8: =COUNTIF('Quadro de Riscos'!$L$4:$L$48,"Extremo")
B9: 2 | C9: =COUNTIFS('Quadro de Riscos'!$I$4:$I$48,2,'Quadro de Riscos'!$J$4:$J$48,1) | D9: =COUNTIFS('Quadro de Riscos'!$I$4:$I$48,2,'Quadro de Riscos'!$J$4:$J$48,2) | E9: =COUNTIFS('Quadro de Riscos'!$I$4:$I$48,2,'Quadro de Riscos'!$J$4:$J$48,3) | F9: =COUNTIFS('Quadro de Riscos'!$I$4:$I$48,2,'Quadro de Riscos'!$J$4:$J$48,4) | G9: =COUNTIFS('Quadro de Riscos'!$I$4:$I$48,2,'Quadro de Riscos'!$J$4:$J$48,5) | I9: Total | J9: =SUM(J5:J8)
B10: 1 | C10: =COUNTIFS('Quadro de Riscos'!$I$4:$I$48,1,'Quadro de Riscos'!$J$4:$J$48,1) | D10: =COUNTIFS('Quadro de Riscos'!$I$4:$I$48,1,'Quadro de Riscos'!$J$4:$J$48,2) | E10: =COUNTIFS('Quadro de Riscos'!$I$4:$I$48,1,'Quadro de Riscos'!$J$4:$J$48,3) | F10: =COUNTIFS('Quadro de Riscos'!$I$4:$I$48,1,'Quadro de Riscos'!$J$4:$J$48,4) | G10: =COUNTIFS('Quadro de Riscos'!$I$4:$I$48,1,'Quadro de Riscos'!$J$4:$J$48,5)
I11: Por categoria
I12: Estratégico | J12: =COUNTIF('Quadro de Riscos'!$B$4:$B$48,"Estratégico")
I13: Financeiro | J13: =COUNTIF('Quadro de Riscos'!$B$4:$B$48,"Financeiro")
I14: Operacional | J14: =COUNTIF('Quadro de Riscos'!$B$4:$B$48,"Operacional")
I15: Regulamentar | J15: =COUNTIF('Quadro de Riscos'!$B$4:$B$48,"Regulamentar")
I16: Integridade | J16: =COUNTIF('Quadro de Riscos'!$B$4:$B$48,"Integridade")
